sleepscienceviewer/AnnotationXmlClass.py
sleepscienceviewer/EdfFileClass.py
sleepscienceviewer/FigureGraphicsViewClass.py
sleepscienceviewer/SignalViewer.py
sleepscienceviewer/SignalWindowClass.py
sleepscienceviewer/SleepScienceViewer.py
sleepscienceviewer/SleepScienceViewerApp.py
sleepscienceviewer/SpectralViewer.py
sleepscienceviewer/SpectralWindowClass.py
sleepscienceviewer/__init__.py
sleepscienceviewer/__main__.py
sleepscienceviewer/logging_config.py
sleepscienceviewer/multitaper_spectrogram_python_class.py
sleepscienceviewer-0.5.1.dist-info/METADATA
sleepscienceviewer-0.5.1.dist-info/WHEEL
sleepscienceviewer-0.5.1.dist-info/entry_points.txt
sleepscienceviewer-0.5.1.dist-info/top_level.txt
sleepscienceviewer-0.5.1.dist-info/RECORD
