Metadata-Version: 2.4
Name: sleepscienceviewer
Version: 0.5.1
Summary: A Python-native EDF and XML annotation viewer for sleep science
Author-email: "Dennis A. Dean, II" <dennis.a.dean@gmail.com>
License-Expression: AGPL-3.0-or-later
Requires-Python: >=3.9
Requires-Dist: PySide6==6.10.0
Requires-Dist: pyside6==6.10.0
Requires-Dist: numpy==2.3.4
Requires-Dist: pandas==2.3.3
Requires-Dist: scipy==1.16.3
Requires-Dist: pyrsdameraulevenshtein==1.1.0
Requires-Dist: matplotlib==3.10.7
Requires-Dist: cmocean==4.0.3
Requires-Dist: colorcet==3.1.0
Requires-Dist: PyWavelets==1.9.0
Requires-Dist: py-ecg-detectors==1.3.5
Requires-Dist: gatspy==0.3
Requires-Dist: openpyxl==3.1.5
Requires-Dist: lxml==6.0.2
Requires-Dist: requests==2.32.5
Requires-Dist: cryptography==46.0.3
Requires-Dist: joblib==1.5.2
Requires-Dist: psutil==7.1.3
Requires-Dist: python-dateutil==2.9.0.post0
Requires-Dist: pytz==2025.2
Requires-Dist: sympy==1.14.0
